README.txt
setup.py
collective/__init__.py
collective.portlet.contentprovider.egg-info/PKG-INFO
collective.portlet.contentprovider.egg-info/SOURCES.txt
collective.portlet.contentprovider.egg-info/dependency_links.txt
collective.portlet.contentprovider.egg-info/entry_points.txt
collective.portlet.contentprovider.egg-info/namespace_packages.txt
collective.portlet.contentprovider.egg-info/not-zip-safe
collective.portlet.contentprovider.egg-info/requires.txt
collective.portlet.contentprovider.egg-info/top_level.txt
collective/portlet/__init__.py
collective/portlet/contentprovider/__init__.py
collective/portlet/contentprovider/configure.zcml
collective/portlet/contentprovider/contentproviderportlet.pt
collective/portlet/contentprovider/contentproviderportlet.py
collective/portlet/contentprovider/interfaces.py
collective/portlet/contentprovider/version.txt
collective/portlet/contentprovider/profiles/default/metadata.xml
collective/portlet/contentprovider/profiles/default/portlets.xml
collective/portlet/contentprovider/tests/__init__.py
collective/portlet/contentprovider/tests/base.py
collective/portlet/contentprovider/tests/test_portlet.py
docs/HISTORY.txt
docs/INSTALL.txt
docs/LICENSE.GPL
docs/LICENSE.txt