Metadata-Version: 1.0
Name: collective.portlet.contentprovider
Version: 1.1
Summary: Renders a content provider in a portlet
Home-page: http://svn.plone.org/svn/collective/
Author: Steve McMahon
Author-email: steve@dcn.org
License: GPL
Keywords: Plone portlet viewlet contentprovider
Platform: UNKNOWN
Classifier: Framework :: Plone
Classifier: Programming Language :: Python
